shade_sorter/__init__.py
shade_sorter/api.py
shade_sorter/classifier.py
shadesorter-0.1.0.dist-info/METADATA
shadesorter-0.1.0.dist-info/WHEEL
shadesorter-0.1.0.dist-info/licenses/LICENSE
shadesorter-0.1.0.dist-info/RECORD
