Metadata-Version: 2.4
Name: ShadeSorter
Version: 0.1.0
Summary: Deterministic color family classifier across HSL, HSV, Lab, and LCH
Project-URL: Homepage, https://github.com/Tintelligence-App/shade-sorter
Project-URL: Repository, https://github.com/Tintelligence-App/shade-sorter
Project-URL: Issues, https://github.com/Tintelligence-App/shade-sorter/issues
Author: Tintelligence
License: MIT License
License-File: LICENSE
Keywords: classification,color,hex,hsl,hsv,lab,lch
Classifier: Intended Audience :: Developers
Classifier: License :: OSI Approved :: MIT License
Classifier: Operating System :: OS Independent
Classifier: Programming Language :: Python :: 3
Classifier: Programming Language :: Python :: 3 :: Only
Classifier: Programming Language :: Python :: 3.9
Classifier: Programming Language :: Python :: 3.10
Classifier: Programming Language :: Python :: 3.11
Classifier: Programming Language :: Python :: 3.12
Classifier: Typing :: Typed
Requires-Python: >=3.9
Requires-Dist: tintelligence-color-utils>=0.1.0
Provides-Extra: dev
Requires-Dist: build>=1.2.1; extra == 'dev'
Requires-Dist: pytest>=7.0; extra == 'dev'
